LICENSE.txt
README.md
setup.cfg
setup.py
hass_flair_api/__init__.py
hass_flair_api/client.py
hass_flair_api.egg-info/PKG-INFO
hass_flair_api.egg-info/SOURCES.txt
hass_flair_api.egg-info/dependency_links.txt
hass_flair_api.egg-info/requires.txt
hass_flair_api.egg-info/top_level.txt