Metadata-Version: 2.1
Name: hass-flair-api
Version: 1.1.1
Summary: Forked Flair API Client
Home-page: https://github.com/RobertD502/flair-api-client-py/tree/hass-flair-api-client
Author: Robert Drinovac
Author-email: unlisted@gmail.com
License: UNKNOWN
Project-URL: Source, https://github.com/RobertD502/flair-api-client-py/tree/hass-flair-api-client
Keywords: flair,flair vents,flair api,flair home assistant
Platform: UNKNOWN
Classifier: Programming Language :: Python :: 3
Classifier: License :: OSI Approved :: MIT License
Classifier: Operating System :: OS Independent
Requires-Python: >=3.6
